{
  "version": "1.0.0",
  "restore": {
    "projectUniqueName": "/Users/kmaric/Projects/examples/Reactive.Example/Reactive.Example.Common/Reactive.Example.Common.csproj",
    "projectName": "Reactive.Example.Common",
    "projectPath": "/Users/kmaric/Projects/examples/Reactive.Example/Reactive.Example.Common/Reactive.Example.Common.csproj",
    "outputPath": "/Users/kmaric/Projects/examples/Reactive.Example/Reactive.Example.Common/obj/",
    "projectStyle": "PackageReference",
    "fallbackFolders": [
      "/usr/local/share/dotnet/sdk/NuGetFallbackFolder"
    ],
    "originalTargetFrameworks": [
      "netcoreapp2.2"
    ],
    "frameworks": {
      "netcoreapp2.2": {
        "projectReferences": {}
      }
    },
    "warningProperties": {
      "warnAsError": [
        "NU1605"
      ]
    }
  },
  "frameworks": {
    "netcoreapp2.2": {
      "dependencies": {
        "Microsoft.AspNetCore.Hosting.Abstractions": {
          "target": "Package",
          "version": "[2.2.0, )"
        },
        "Microsoft.AspNetCore.Http.Abstractions": {
          "target": "Package",
          "version": "[2.2.0, )"
        },
        "Microsoft.Extensions.Options": {
          "target": "Package",
          "version": "[2.2.0, )"
        },
        "Microsoft.NETCore.App": {
          "suppressParent": "All",
          "target": "Package",
          "version": "[2.2.0, )",
          "autoReferenced": true
        },
        "RabbitMQ.Client": {
          "target": "Package",
          "version": "[5.1.0, )"
        }
      },
      "imports": [
        "net461"
      ],
      "assetTargetFallback": true,
      "warn": true
    }
  }
}